{"stats":{"minecraft:picked_up":{"create:metal_bracket":6,"create:wooden_bracket":7,"cmi:super_knife":1,"create:brass_tunnel":3,"create:andesite_tunnel":3,"create:brass_ingot":1,"minecraft:diamond":32,"vintageimprovements:redstone_module":1},"minecraft:custom":{"minecraft:open_barrel":4,"minecraft:leave_game":5,"minecraft:time_since_death":488718,"minecraft:time_since_rest":488718,"minecraft:sprint_one_cm":41948,"minecraft:walk_one_cm":99532,"minecraft:drop":5,"minecraft:fly_one_cm":1472353,"minecraft:open_chest":2,"minecraft:crouch_one_cm":1895,"minecraft:play_time":488718,"minecraft:sneak_time":7458,"minecraft:jump":533,"minecraft:total_world_time":537042},"minecraft:dropped":{"thermal_extra:amethyst_dust":1,"createaddition:electrum_sheet":1,"create:wooden_bracket":1,"minecraft:gold_ingot":2},"minecraft:used":{"cmi:ponder_thermal_machine_side":10,"tconstruct:cobalt_block":23,"create:deployer":14,"create:brass_block":13,"cmi:ponder_thermal_machine_front":3,"create:brass_casing":67,"create:polished_cut_ochrum":5,"ae2:charger":1,"create:small_rose_quartz_tiles":1,"create:crushing_wheel":6,"rechiseled:redstone_block_diagonal_tiles_connecting":19,"createdeco:brass_catwalk_stairs":4,"create:wooden_bracket":8,"cmi:ponder_thermal_water":2,"minecraft:smooth_quartz_slab":7,"immersiveengineering:radiator":1,"createaddition:connector":6,"cmi:ponder_thermal_arrow":2,"create:brass_tunnel":31,"minecraft:chest":1,"immersiveengineering:sheetmetal_steel":3,"immersiveengineering:treated_scaffold":4,"farmersdelight:rice_bag":2,"create:small_ochrum_bricks":127,"createaddition:copper_spool":6,"create:railway_casing":1,"cmi:green_screen":13,"minecraft:structure_block":61,"minecraft:netherrack":66,"create:mechanical_saw":6,"create:blaze_burner":2,"minecraft:polished_blackstone_bricks":25,"createdeco:andesite_catwalk_stairs":10,"create_connected:fan_blasting_catalyst":1,"create:spout":9,"cmi:ponder_thermal_slot":4,"cmi:ponder_thermal_energy":4,"minecraft:dirt":17,"create:mechanical_pump":2,"ae2:quartz_bricks":2,"vintageimprovements:laser":7,"create:encased_fan":1,"create:brass_funnel":30,"create:mechanical_mixer":6,"cmi:ponder_thermal_machine_top":62,"createaddition:rolling_mill":3,"create:cogwheel":8,"cmi:ponder_thermal_fire":2,"vintageimprovements:belt_grinder":6,"cmi:fiber_optics":1,"cmi:water_pump":1,"immersiveengineering:treated_wood_horizontal":12,"cmi:ponder_thermal_gui_blue_icon":1,"create:depot":2,"create:metal_girder":29,"cmi:ponder_thermal_gui_lightblue_icon":3,"rechiseled:obsidian_brick_paving_connecting":5,"cmi:ponder_thermal_machine_bottom":33,"createdeco:andesite_catwalk":164,"create:chute":9,"create:track":18,"rechiseled:redstone_block_bordered_connecting":18,"mbd2:accelerator":12,"create:mechanical_press":9,"cmi:ponder_thermal_gui_red_icon":1,"cmi:ponder_thermal_fluid":2,"immersiveengineering:treated_fence":8,"create:wrench":34,"minecraft:cracked_polished_blackstone_bricks":5,"cmi:ponder_thermal_energy_empty":4,"minecraft:grass_block":8,"tconstruct:seared_table":1,"cmi:ponder_thermal_gui_green_icon":1,"create:metal_bracket":2,"ae2:quartz_block":119,"createaddition:creative_energy":3,"createdeco:brass_catwalk":550,"tconstruct:seared_faucet":1,"create:millstone":3,"minecraft:smooth_quartz":1,"create:andesite_tunnel":1,"create:creative_motor":6,"createaddition:tesla_coil":6,"createdeco:zinc_catwalk":532,"rechiseled:obsidian_bricks_connecting":4,"create:polished_cut_calcite":1,"create:basin":7,"immersiveengineering:slab_steel_scaffolding_standard":1,"create:shaft":198,"cmi:ponder_thermal_slot_energy":3,"mbd2:mbd_gadgets":5,"vintageimprovements:spring_coiling_machine":1,"create:fluid_pipe":61,"immersiveengineering:stairs_treated_wood_horizontal":4,"ae2:cut_quartz_block":63,"cmi:ponder_thermal_gui_gray_icon":1,"tconstruct:cobalt_ore":5,"create:vertical_gearbox":11,"cmi:ponder_thermal_gui":32,"create:polished_cut_deepslate":37,"create:belt_connector":176,"createdeco:iron_catwalk":201}},"DataVersion":3465}